Workbook

Sheet Summary
A1: ATIP feature status tracker
A2: Source: docs/ATIP_MASTER_TRACKER.csv (dev branch, incl. W25) as of 2026-09-28; production release ATIP-W24-RC1 deployed 2026-09-28 11:31; W25 built, not deployed.
A4: Phase | B4: Phase name | C4: Completed | D4: Built, needs QA | E4: In progress | F4: Yet to start | G4: Blocked | H4: Unclear | I4: Total | J4: Done or built % | K4: Avg completion %
A5: 0 | B5: Delivered baseline (maintain) | C5: =COUNTIFS('All Features'!$B$2:$B$278,$A5,'All Features'!$G$2:$G$278,"COMPLETED") | D5: =COUNTIFS('All Features'!$B$2:$B$278,$A5,'All Features'!$G$2:$G$278,"IMPLEMENTED BUT NOT VERIFIED") | E5: =COUNTIFS('All Features'!$B$2:$B$278,$A5,'All Features'!$G$2:$G$278,"IN PROGRESS") | F5: =COUNTIFS('All Features'!$B$2:$B$278,$A5,'All Features'!$G$2:$G$278,"YET TO START") | G5: =COUNTIFS('All Features'!$B$2:$B$278,$A5,'All Features'!$G$2:$G$278,"BLOCKED") | H5: =COUNTIFS('All Features'!$B$2:$B$278,$A5,'All Features'!$G$2:$G$278,"UNCLEAR") | I5: =SUM(C5:H5) | J5: =IF(I5=0,0,(C5+D5)/I5) | K5: =IFERROR(AVERAGEIFS('All Features'!$H$2:$H$278,'All Features'!$B$2:$B$278,$A5),0)
A6: 1 | B6: Foundation | C6: =COUNTIFS('All Features'!$B$2:$B$278,$A6,'All Features'!$G$2:$G$278,"COMPLETED") | D6: =COUNTIFS('All Features'!$B$2:$B$278,$A6,'All Features'!$G$2:$G$278,"IMPLEMENTED BUT NOT VERIFIED") | E6: =COUNTIFS('All Features'!$B$2:$B$278,$A6,'All Features'!$G$2:$G$278,"IN PROGRESS") | F6: =COUNTIFS('All Features'!$B$2:$B$278,$A6,'All Features'!$G$2:$G$278,"YET TO START") | G6: =COUNTIFS('All Features'!$B$2:$B$278,$A6,'All Features'!$G$2:$G$278,"BLOCKED") | H6: =COUNTIFS('All Features'!$B$2:$B$278,$A6,'All Features'!$G$2:$G$278,"UNCLEAR") | I6: =SUM(C6:H6) | J6: =IF(I6=0,0,(C6+D6)/I6) | K6: =IFERROR(AVERAGEIFS('All Features'!$H$2:$H$278,'All Features'!$B$2:$B$278,$A6),0)
A7: 2 | B7: Quant Research (data, factors, backtesting) | C7: =COUNTIFS('All Features'!$B$2:$B$278,$A7,'All Features'!$G$2:$G$278,"COMPLETED") | D7: =COUNTIFS('All Features'!$B$2:$B$278,$A7,'All Features'!$G$2:$G$278,"IMPLEMENTED BUT NOT VERIFIED") | E7: =COUNTIFS('All Features'!$B$2:$B$278,$A7,'All Features'!$G$2:$G$278,"IN PROGRESS") | F7: =COUNTIFS('All Features'!$B$2:$B$278,$A7,'All Features'!$G$2:$G$278,"YET TO START") | G7: =COUNTIFS('All Features'!$B$2:$B$278,$A7,'All Features'!$G$2:$G$278,"BLOCKED") | H7: =COUNTIFS('All Features'!$B$2:$B$278,$A7,'All Features'!$G$2:$G$278,"UNCLEAR") | I7: =SUM(C7:H7) | J7: =IF(I7=0,0,(C7+D7)/I7) | K7: =IFERROR(AVERAGEIFS('All Features'!$H$2:$H$278,'All Features'!$B$2:$B$278,$A7),0)
A8: 3 | B8: Strategy Engine | C8: =COUNTIFS('All Features'!$B$2:$B$278,$A8,'All Features'!$G$2:$G$278,"COMPLETED") | D8: =COUNTIFS('All Features'!$B$2:$B$278,$A8,'All Features'!$G$2:$G$278,"IMPLEMENTED BUT NOT VERIFIED") | E8: =COUNTIFS('All Features'!$B$2:$B$278,$A8,'All Features'!$G$2:$G$278,"IN PROGRESS") | F8: =COUNTIFS('All Features'!$B$2:$B$278,$A8,'All Features'!$G$2:$G$278,"YET TO START") | G8: =COUNTIFS('All Features'!$B$2:$B$278,$A8,'All Features'!$G$2:$G$278,"BLOCKED") | H8: =COUNTIFS('All Features'!$B$2:$B$278,$A8,'All Features'!$G$2:$G$278,"UNCLEAR") | I8: =SUM(C8:H8) | J8: =IF(I8=0,0,(C8+D8)/I8) | K8: =IFERROR(AVERAGEIFS('All Features'!$H$2:$H$278,'All Features'!$B$2:$B$278,$A8),0)
A9: 4 | B9: AI/ML | C9: =COUNTIFS('All Features'!$B$2:$B$278,$A9,'All Features'!$G$2:$G$278,"COMPLETED") | D9: =COUNTIFS('All Features'!$B$2:$B$278,$A9,'All Features'!$G$2:$G$278,"IMPLEMENTED BUT NOT VERIFIED") | E9: =COUNTIFS('All Features'!$B$2:$B$278,$A9,'All Features'!$G$2:$G$278,"IN PROGRESS") | F9: =COUNTIFS('All Features'!$B$2:$B$278,$A9,'All Features'!$G$2:$G$278,"YET TO START") | G9: =COUNTIFS('All Features'!$B$2:$B$278,$A9,'All Features'!$G$2:$G$278,"BLOCKED") | H9: =COUNTIFS('All Features'!$B$2:$B$278,$A9,'All Features'!$G$2:$G$278,"UNCLEAR") | I9: =SUM(C9:H9) | J9: =IF(I9=0,0,(C9+D9)/I9) | K9: =IFERROR(AVERAGEIFS('All Features'!$H$2:$H$278,'All Features'!$B$2:$B$278,$A9),0)
A10: 5 | B10: Risk & Portfolio | C10: =COUNTIFS('All Features'!$B$2:$B$278,$A10,'All Features'!$G$2:$G$278,"COMPLETED") | D10: =COUNTIFS('All Features'!$B$2:$B$278,$A10,'All Features'!$G$2:$G$278,"IMPLEMENTED BUT NOT VERIFIED") | E10: =COUNTIFS('All Features'!$B$2:$B$278,$A10,'All Features'!$G$2:$G$278,"IN PROGRESS") | F10: =COUNTIFS('All Features'!$B$2:$B$278,$A10,'All Features'!$G$2:$G$278,"YET TO START") | G10: =COUNTIFS('All Features'!$B$2:$B$278,$A10,'All Features'!$G$2:$G$278,"BLOCKED") | H10: =COUNTIFS('All Features'!$B$2:$B$278,$A10,'All Features'!$G$2:$G$278,"UNCLEAR") | I10: =SUM(C10:H10) | J10: =IF(I10=0,0,(C10+D10)/I10) | K10: =IFERROR(AVERAGEIFS('All Features'!$H$2:$H$278,'All Features'!$B$2:$B$278,$A10),0)
A11: 6 | B11: Execution | C11: =COUNTIFS('All Features'!$B$2:$B$278,$A11,'All Features'!$G$2:$G$278,"COMPLETED") | D11: =COUNTIFS('All Features'!$B$2:$B$278,$A11,'All Features'!$G$2:$G$278,"IMPLEMENTED BUT NOT VERIFIED") | E11: =COUNTIFS('All Features'!$B$2:$B$278,$A11,'All Features'!$G$2:$G$278,"IN PROGRESS") | F11: =COUNTIFS('All Features'!$B$2:$B$278,$A11,'All Features'!$G$2:$G$278,"YET TO START") | G11: =COUNTIFS('All Features'!$B$2:$B$278,$A11,'All Features'!$G$2:$G$278,"BLOCKED") | H11: =COUNTIFS('All Features'!$B$2:$B$278,$A11,'All Features'!$G$2:$G$278,"UNCLEAR") | I11: =SUM(C11:H11) | J11: =IF(I11=0,0,(C11+D11)/I11) | K11: =IFERROR(AVERAGEIFS('All Features'!$H$2:$H$278,'All Features'!$B$2:$B$278,$A11),0)
A12: 7 | B12: Advanced Quant | C12: =COUNTIFS('All Features'!$B$2:$B$278,$A12,'All Features'!$G$2:$G$278,"COMPLETED") | D12: =COUNTIFS('All Features'!$B$2:$B$278,$A12,'All Features'!$G$2:$G$278,"IMPLEMENTED BUT NOT VERIFIED") | E12: =COUNTIFS('All Features'!$B$2:$B$278,$A12,'All Features'!$G$2:$G$278,"IN PROGRESS") | F12: =COUNTIFS('All Features'!$B$2:$B$278,$A12,'All Features'!$G$2:$G$278,"YET TO START") | G12: =COUNTIFS('All Features'!$B$2:$B$278,$A12,'All Features'!$G$2:$G$278,"BLOCKED") | H12: =COUNTIFS('All Features'!$B$2:$B$278,$A12,'All Features'!$G$2:$G$278,"UNCLEAR") | I12: =SUM(C12:H12) | J12: =IF(I12=0,0,(C12+D12)/I12) | K12: =IFERROR(AVERAGEIFS('All Features'!$H$2:$H$278,'All Features'!$B$2:$B$278,$A12),0)
A13: 8 | B13: Production Hardening | C13: =COUNTIFS('All Features'!$B$2:$B$278,$A13,'All Features'!$G$2:$G$278,"COMPLETED") | D13: =COUNTIFS('All Features'!$B$2:$B$278,$A13,'All Features'!$G$2:$G$278,"IMPLEMENTED BUT NOT VERIFIED") | E13: =COUNTIFS('All Features'!$B$2:$B$278,$A13,'All Features'!$G$2:$G$278,"IN PROGRESS") | F13: =COUNTIFS('All Features'!$B$2:$B$278,$A13,'All Features'!$G$2:$G$278,"YET TO START") | G13: =COUNTIFS('All Features'!$B$2:$B$278,$A13,'All Features'!$G$2:$G$278,"BLOCKED") | H13: =COUNTIFS('All Features'!$B$2:$B$278,$A13,'All Features'!$G$2:$G$278,"UNCLEAR") | I13: =SUM(C13:H13) | J13: =IF(I13=0,0,(C13+D13)/I13) | K13: =IFERROR(AVERAGEIFS('All Features'!$H$2:$H$278,'All Features'!$B$2:$B$278,$A13),0)
A14: 8 | B14: Production hardening | C14: =COUNTIFS('All Features'!$B$2:$B$278,$A14,'All Features'!$G$2:$G$278,"COMPLETED") | D14: =COUNTIFS('All Features'!$B$2:$B$278,$A14,'All Features'!$G$2:$G$278,"IMPLEMENTED BUT NOT VERIFIED") | E14: =COUNTIFS('All Features'!$B$2:$B$278,$A14,'All Features'!$G$2:$G$278,"IN PROGRESS") | F14: =COUNTIFS('All Features'!$B$2:$B$278,$A14,'All Features'!$G$2:$G$278,"YET TO START") | G14: =COUNTIFS('All Features'!$B$2:$B$278,$A14,'All Features'!$G$2:$G$278,"BLOCKED") | H14: =COUNTIFS('All Features'!$B$2:$B$278,$A14,'All Features'!$G$2:$G$278,"UNCLEAR") | I14: =SUM(C14:H14) | J14: =IF(I14=0,0,(C14+D14)/I14) | K14: =IFERROR(AVERAGEIFS('All Features'!$H$2:$H$278,'All Features'!$B$2:$B$278,$A14),0)
A15: 9 | B15: Enterprise SaaS (final objective) | C15: =COUNTIFS('All Features'!$B$2:$B$278,$A15,'All Features'!$G$2:$G$278,"COMPLETED") | D15: =COUNTIFS('All Features'!$B$2:$B$278,$A15,'All Features'!$G$2:$G$278,"IMPLEMENTED BUT NOT VERIFIED") | E15: =COUNTIFS('All Features'!$B$2:$B$278,$A15,'All Features'!$G$2:$G$278,"IN PROGRESS") | F15: =COUNTIFS('All Features'!$B$2:$B$278,$A15,'All Features'!$G$2:$G$278,"YET TO START") | G15: =COUNTIFS('All Features'!$B$2:$B$278,$A15,'All Features'!$G$2:$G$278,"BLOCKED") | H15: =COUNTIFS('All Features'!$B$2:$B$278,$A15,'All Features'!$G$2:$G$278,"UNCLEAR") | I15: =SUM(C15:H15) | J15: =IF(I15=0,0,(C15+D15)/I15) | K15: =IFERROR(AVERAGEIFS('All Features'!$H$2:$H$278,'All Features'!$B$2:$B$278,$A15),0)
A16: 10 | B16: Wealth track (Waves 11-20) | C16: =COUNTIFS('All Features'!$B$2:$B$278,$A16,'All Features'!$G$2:$G$278,"COMPLETED") | D16: =COUNTIFS('All Features'!$B$2:$B$278,$A16,'All Features'!$G$2:$G$278,"IMPLEMENTED BUT NOT VERIFIED") | E16: =COUNTIFS('All Features'!$B$2:$B$278,$A16,'All Features'!$G$2:$G$278,"IN PROGRESS") | F16: =COUNTIFS('All Features'!$B$2:$B$278,$A16,'All Features'!$G$2:$G$278,"YET TO START") | G16: =COUNTIFS('All Features'!$B$2:$B$278,$A16,'All Features'!$G$2:$G$278,"BLOCKED") | H16: =COUNTIFS('All Features'!$B$2:$B$278,$A16,'All Features'!$G$2:$G$278,"UNCLEAR") | I16: =SUM(C16:H16) | J16: =IF(I16=0,0,(C16+D16)/I16) | K16: =IFERROR(AVERAGEIFS('All Features'!$H$2:$H$278,'All Features'!$B$2:$B$278,$A16),0)
B17: TOTAL | C17: =SUM(C5:C16) | D17: =SUM(D5:D16) | E17: =SUM(E5:E16) | F17: =SUM(F5:F16) | G17: =SUM(G5:G16) | H17: =SUM(H5:H16) | I17: =SUM(I5:I16) | J17: =IF(I17=0,0,(C17+D17)/I17) | K17: =AVERAGE('All Features'!$H$2:$H$278)
A19: Other counts
A20: Features needing independent QA (built, not verified) | I20: =COUNTIF('All Features'!$G$2:$G$278,"IMPLEMENTED BUT NOT VERIFIED")
A21: Features waiting on an owner decision | I21: =COUNTIF('All Features'!$K$2:$K$278,"*Owner:*")
A22: Owner decisions still open | I22: =COUNTBLANK('Owner Decisions'!$F$2:$F$18)
A23: Reviewed OK | I23: =COUNTIF('All Features'!$Q$2:$Q$278,"Reviewed OK")
A24: Reviewed with an issue | I24: =COUNTIF('All Features'!$Q$2:$Q$278,"Issue found")
A25: Open issues | I25: =COUNTIF('Open Issues'!$E$2:$E$8,"OPEN")
A27: How to use this workbook
A28: Yellow cells are yours to fill: 'All Features' columns Review Status (drop-down) and Reviewer Notes; 'Owner Decisions' columns Your decision and Date.
A29: Example: Review Status = Issue found; Reviewer Notes = 'Goal Monte Carlo slow with 20 goals (8 s) - retest after fix'.
A30: Status meanings: COMPLETED = built (W1/W2 tested); IMPLEMENTED BUT NOT VERIFIED = built and smoke-run, awaiting independent QA; IN PROGRESS = partly built; YET TO START = not built.
A31: Every count above is a live formula over 'All Features': filter or edit that sheet and the summary updates.
A32: 'Deployed' means the code is in the running production release ATIP-W24-RC1; new features stay off until their config switch is enabled (see Owner Decisions).

Sheet All Features
A1: Seq | B1: Phase | C1: Phase Name | D1: ID | E1: Module | F1: Feature | G1: Status | H1: Completion % | I1: Wave | J1: Deployed | K1: Needs | L1: Current Implementation | M1: Next Action / Missing Work | N1: Key Files | O1: Depends On | P1: Last Updated | Q1: Review Status | R1: Reviewer Notes
A2: 1 | B2: 0 | C2: Delivered baseline (maintain) | D2: DP-02 | E2: Data Platform | F2: Daily OHLCV history | G2: COMPLETED | H2: 0.9 | J2: Live (ATIP-W24-RC1) | L2: NSE Bhavcopy + Dhan; coverage/freshness/duplicate guards | M2: Maintain | N2: data/bhavcopy.py; data/dhan.py | P2: 2026-09-24
A3: 2 | B3: 0 | C3: Delivered baseline (maintain) | D3: DP-07 | E3: Data Platform | F3: Delivery data | G3: COMPLETED | H3: 0.9 | J3: Live (ATIP-W24-RC1) | L3: Full Bhavcopy nightly + backfill | M3: Maintain | N3: data/bhavcopy.py | P3: 2026-09-24
A4: 3 | B4: 0 | C4: Delivered baseline (maintain) | D4: DP-20 | E4: Data Platform | F4: Trading calendar | G4: COMPLETED | H4: 0.9 | J4: Live (ATIP-W24-RC1) | L4: 2025-26 holidays + budget sessions | M4: Add next year's holidays each December | N4: utils/trading_calendar.py | P4: 2026-09-24
A5: 4 | B5: 0 | C5: Delivered baseline (maintain) | D5: TA-01 | E5: Technical Analysis | F5: Core indicators | G5: COMPLETED | H5: 0.9 | J5: Live (ATIP-W24-RC1) | L5: Computed and stored; MACD fixed and normalised | M5: Maintain | N5: data/technical.py | P5: 2026-09-24
A6: 5 | B6: 0 | C6: Delivered baseline (maintain) | D6: TA-02 | E6: Technical Analysis | F6: Extended oscillators | G6: COMPLETED | H6: 0.8 | J6: Live (ATIP-W24-RC1) | L6: Computed and stored | M6: Maintain | N6: data/technical.py | P6: 2026-09-24
A7: 6 | B7: 0 | C7: Delivered baseline (maintain) | D7: TA-05 | E7: Technical Analysis | F7: Fibonacci | G7: COMPLETED | H7: 0.8 | J7: Live (ATIP-W24-RC1) | L7: 52-week 23.6/38.2/50/61.8 levels | M7: Optional: swing-anchored levels | N7: data/technical.py | P7: 2026-09-24
A8: 7 | B8: 0 | C8: Delivered baseline (maintain) | D8: TA-07 | E8: Technical Analysis | F8: Trend features | G8: COMPLETED | H8: 0.8 | J8: Live (ATIP-W24-RC1) | L8: Computed and stored | M8: Maintain | N8: data/technical.py | P8: 2026-09-24
A9: 8 | B9: 0 | C9: Delivered baseline (maintain) | D9: TA-08 | E9: Technical Analysis | F9: Relative strength | G9: COMPLETED | H9: 0.8 | J9: Live (ATIP-W24-RC1) | L9: 20-day RS with date-matched benchmark | M9: Sector-relative RS later (TA-08b in Phase 2 if wanted) | N9: scores/engine.py | P9: 2026-09-24
A10: 9 | B10: 0 | C10: Delivered baseline (maintain) | D10: SC-03 | E10: Alpha/Factor Engine | F10: RRI | G10: COMPLETED | H10: 0.75 | J10: Live (ATIP-W24-RC1) | L10: Implemented | M10: Institutional input improves with SC-14 | N10: scores/engine.py | P10: 2026-09-24
A11: 10 | B11: 0 | C11: Delivered baseline (maintain) | D11: SC-04 | E11: Alpha/Factor Engine | F11: MRI | G11: COMPLETED | H11: 0.85 | J11: Live (ATIP-W24-RC1) | L11: Implemented; MACD corrected | M11: Maintain | N11: scores/engine.py | P11: 2026-09-24
A12: 11 | B12: 0 | C12: Delivered baseline (maintain) | D12: SC-07 | E12: Alpha/Factor Engine | F12: ZPI | G12: COMPLETED | H12: 0.8 | J12: Live (ATIP-W24-RC1) | L12: Implemented + delivery component | M12: Maintain | N12: scores/engine.py | P12: 2026-09-24
A13: 12 | B13: 0 | C13: Delivered baseline (maintain) | D13: SC-10 | E13: Alpha/Factor Engine | F13: Portfolio Health score | G13: COMPLETED | H13: 0.75 | J13: Live (ATIP-W24-RC1) | L13: Implemented | M13: Correlation/drawdown inputs come with PF-09 and PF-13 | N13: scores/portfolio_health.py | P13: 2026-09-24
... A60: 59 | B60: 1 | C60: Foundation | D60: DP-09 | E60: Data Platform | F60: India VIX | G60: COMPLETED | H60: 0.95 | J60: Live (ATIP-W24-RC1) | L60: Daily INDIAVIX series in prices_daily (421 sessions 2025-01-13..; Dhan history + NSE close nightly); get_vix() = session feed then daily series; no 15.0 default | M60: None for DP-09; VIX term structure/percentile features belong to later factor work | N60: scores/engine.py; data/dhan.py; data/bhavcopy.py; pipeline/scheduler.py; main.py | P60: 2026-09-24
A61: 60 | B61: 1 | C61: Foundation | D61: DP-17 | E61: Data Platform | F61: Market breadth | G61: COMPLETED | H61: 0.9 | J61: Live (ATIP-W24-RC1) | L61: breadth_series(): advances/declines; % advancing; A/D ratio; % above 200-DMA; 52-week new highs/lows over tracked universe; 80% coverage gate; stored in market_health | M61: Survivorship-free universe (BT-15); sector-level breadth (DP-13) | N61: scores/engine.py; db/schema.py | O61: DP-02 | P61: 2026-09-24
A62: 61 | B62: 1 | C62: Foundation | D62: SC-09 | E62: Alpha/Factor Engine | F62: Market Health score | G62: COMPLETED | H62: 0.9 | J62: Live (ATIP-W24-RC1) | L62: Every MH input is real or left out (index_levels then daily index series; session-own FII/DII; global <=4 days; VIX; breadth); coverage + inputs stored; no score below 50% coverage; upsert keeps portfolio_health; 393 past sessions backfilled | M62: FII/DII and global history only from 2026-07 (backfilled coverage avg 0.65); determine_signal still defaults a missing MH to 50; model-based regime is ML-05 | N62: scores/engine.py; data/dhan.py; data/bhavcopy.py; pipeline/scheduler.py; main.py | O62: DP-09; DP-17 | P62: 2026-09-24
A63: 62 | B63: 1 | C63: Foundation | D63: SC-08 | E63: Alpha/Factor Engine | F63: ACS | G63: COMPLETED | H63: 0.85 | J63: Live (ATIP-W24-RC1) | L63: HistoricalAccuracy = 90-day 5-session hit rate from outcomes known by the scored day (min 5); NewsConfidence only from AI-classified news with no look-ahead; missing inputs left out (no 50/60 stand-ins) | M63: NewsConfidence stays absent until NS-02 (Anthropic key) classifies news | N63: scores/engine.py; data/news.py; db/schema.py | O63: SC-09 | P63: 2026-09-24
A64: 63 | B64: 1 | C64: Foundation | D64: MON-01 | E64: Monitoring | F64: Job logging | G64: COMPLETED | H64: 0.9 | J64: Live (ATIP-W24-RC1) | L64: run_job records every run (start/end/duration/rows/status/error); returned FAILED is a failure; EMPTY status | M64: Record failures, end time, row counts | N64: pipeline/scheduler.py; db/schema.py | P64: 2026-09-24
A65: 64 | B65: 1 | C65: Foundation | D65: MON-02 | E65: Monitoring | F65: Stalled-job detection | G65: COMPLETED | H65: 0.85 | J65: Live (ATIP-W24-RC1) | L65: pipeline/health.py expectations: MISSED/STALLED/FAILING/EMPTY; every 30 min | M65: Expected-run table + missed-run check | N65: pipeline/health.py; pipeline/scheduler.py | O65: MON-01 | P65: 2026-09-24
A66: 65 | B66: 1 | C66: Foundation | D66: MON-03 | E66: Monitoring | F66: Failure alerting | G66: COMPLETED | H66: 0.85 | J66: Live (ATIP-W24-RC1) | L66: alert_log + dashboard panel + Telegram when configured; daily de-dup; token scrubbed | M66: Configure Telegram; alert on failure/stall | N66: alerts/telegram.py; dashboard/server.py | O66: MON-02 | P66: 2026-09-24
A67: 66 | B67: 1 | C67: Foundation | D67: DB-14 | E67: Dashboard | F67: Alerts / morning brief | G67: COMPLETED | H67: 0.8 | J67: Live (ATIP-W24-RC1) | L67: Brief recorded for the dashboard + Telegram; pipeline-health section (outside W1, same tree) | M67: Deliver digest; verify daily | N67: alerts/telegram.py | O67: MON-03 | P67: 2026-09-24
A68: 67 | B68: 1 | C68: Foundation | D68: RK-15 | E68: Risk Management | F68: Risk alerts | G68: COMPLETED | H68: 0.8 | J68: Live (ATIP-W24-RC1) | L68: Alerts on halt/resume and on halted or limit-refused orders (outside W1, same tree) | M68: Alert on halt, limit breach, CRI spike | N68: orders/risk.py; orders/broker.py | O68: MON-03 | P68: 2026-09-24
A69: 68 | B69: 1 | C69: Foundation | D69: MON-06 | E69: Monitoring | F69: Log rotation | G69: COMPLETED | H69: 0.9 | J69: Live (ATIP-W24-RC1) | L69: SafeRotatingFileHandler 20 MB x 10, survives refused rename (outside W1, same tree) | M69: RotatingFileHandler | N69: main.py | P69: 2026-09-24
A70: 69 | B70: 1 | C70: Foundation | D70: DBS-06 | E70: Database | F70: Timestamp consistency | G70: COMPLETED | H70: 0.85 | J70: Live (ATIP-W24-RC1) | L70: Convention documented (IST; created_at UTC); news UTC->IST; status query fixed; repair tool | M70: Normalise; fix news recency | N70: db/schema.py; data/news.py; tools/repair_news_timezone.py | P70: 2026-09-24
A71: 70 | B71: 1 | C71: Foundation | D71: NS-01 | E71: News/Sentiment | F71: News ingestion | G71: COMPLETED | H71: 0.8 | J71: Live (ATIP-W24-RC1) | L71: News first + morning catch-up; de-dup; per-feed status; 4 more RSS feeds | M71: Fix job; add second source; health check | N71: data/news.py; pipeline/scheduler.py | O71: MON-02 | P71: 2026-09-24
A72: 71 | B72: 1 | C72: Foundation | D72: OPS-03 | E72: Deployment/Ops | F72: Install/setup | G72: COMPLETED | H72: 0.85 | J72: Live (ATIP-W24-RC1) | L72: ta not pandas-ta everywhere; requirements-dev.txt; CI httpx; config template; docs/DEV_SETUP.md | M72: Fix requirements/setup; pin versions | N72: setup.py; install.bat; requirements-dev.txt; docs/DEV_SETUP.md | P72: 2026-09-24
A73: 72 | B73: 1 | C73: Foundation | D73: EX-01 | E73: Execution | F73: Order management tests | G73: COMPLETED | H73: 0.7 | J73: Live (ATIP-W24-RC1) | L73: orders/rules.py (944 lines) without tests | M73: Unit tests for rules.py | N73: orders/rules.py; tests/ | P73: 2026-09-24
A74: 73 | B74: 1 | C74: Foundation | D74: OPS-02 | E74: Deployment/Ops | F74: CI + end-to-end test | G74: COMPLETED | H74: 0.7 | J74: Live (ATIP-W24-RC1) | L74: GitHub Actions; ~270 test functions; no E2E | M74: Add E2E pipeline test | N74: .github/workflows/tests.yml; tests/ | O74: EX-01 | P74: 2026-09-24
A75: 74 | B75: 1 | C75: Foundation | D75: DP-15 | E75: Data Platform | F75: Fundamentals | G75: IN PROGRESS | H75: 0.3 | J75: — | K75: Owner: Enable fundamentals ingestion (Screener.in) | L75: Screener.in fetcher; ingestion disabled | M75: Your decision; enable; quarterly store; no 50.0 default | N75: data/fundamentals.py; pipeline/scheduler.py | P75: 2026-09-24
A76: 75 | B76: 1 | C76: Foundation | D76: SC-13 | E76: Alpha/Factor Engine | F76: Fundamental Score | G76: IN PROGRESS | H76: 0.2 | J76: — | K76: Development | L76: Default 50 when unparsed | M76: Implement FS formula on real data | N76: data/fundamentals.py | O76: DP-15 | P76: 2026-09-24
A77: 76 | B77: 1 | C77: Foundation | D77: SC-02 | E77: Alpha/Factor Engine | F77: SPI | G77: IN PROGRESS | H77: 0.3 | J77: — | K77: Development | L77: =fundamental_score (double-weighted) | M77: Implement SPI formula separately from FS | N77: scores/engine.py | O77: SC-13 | P77: 2026-09-24
A78: 77 | B78: 1 | C78: Foundation | D78: SC-05 | E78: Alpha/Factor Engine | F78: CRI debt input | G78: COMPLETED | H78: 0.75 | J78: Live (ATIP-W24-RC1) | L78: Implemented; Debt input missing | M78: Feed Debt/Equity | N78: scores/engine.py | O78: DP-15 | P78: 2026-09-24
A79: 78 | B79: 1 | C79: Foundation | D79: SC-01 | E79: Alpha/Factor Engine | F79: VPI inputs | G79: COMPLETED | H79: 0.8 | J79: Live (ATIP-W24-RC1) | L79: Implemented; FG/IS inputs weak | M79: Real Fundamental Growth input | N79: scores/engine.py | O79: DP-15 | P79: 2026-09-24
A80: 79 | B80: 1 | C80: Foundation | D80: PF-01 | E80: Portfolio | F80: Portfolio ingestion | G80: COMPLETED | H80: 0.8 | J80: Live (ATIP-W24-RC1) | L80: portfolio_sync records each attempt and reason (DH-901 named); qty/avg update; sold removed | M80: Scheduled reliable sync + token handling | N80: data/dhan.py; portfolio/zerodha.py | P80: 2026-09-24
A81: 80 | B81: 1 | C81: Foundation | D81: BR-04 | E81: Broker Integration | F81: Portfolio sync schedule | G81: COMPLETED | H81: 0.8 | J81: Live (ATIP-W24-RC1) | L81: Morning catch-up re-sync; Zerodha SKIPPED when not connected; health expects SUCCESS | M81: Scheduled sync with alert on failure | N81: pipeline/scheduler.py; pipeline/health.py | O81: PF-01 | P81: 2026-09-24
A82: 81 | B82: 1 | C82: Foundation | D82: PF-02 | E82: Portfolio | F82: Holdings & P&L | G82: COMPLETED | H82: 0.8 | J82: Live (ATIP-W24-RC1) | L82: portfolio/pnl.py PAPER + LIVE books marked to market; /api/pnl | M82: Realised + unrealised P&L | N82: portfolio/pnl.py; dashboard/server.py | O82: PF-01 | P82: 2026-09-24
A83: 82 | B83: 1 | C83: Foundation | D83: PF-13 | E83: Portfolio | F83: Daily P&L series | G83: COMPLETED | H83: 0.85 | J83: Live (ATIP-W24-RC1) | L83: pnl_daily equity/day P&L/peak/drawdown per env; post-market daily_pnl job | M83: Daily P&L table; EOD job | N83: portfolio/pnl.py; db/schema.py | O83: PF-02 | P83: 2026-09-24
A84: 83 | B84: 1 | C84: Foundation | D84: RK-13 | E84: Risk Management | F84: Risk-based sizing wired to orders | G84: COMPLETED | H84: 0.85 | J84: Live (ATIP-W24-RC1) | L84: size_position() pure + size_for_account(); quantity_type RISK in order rules | M84: Use size in order path | N84: orders/risk.py; orders/rules.py | P84: 2026-09-24
A85: 84 | B85: 1 | C85: Foundation | D85: RK-07 | E85: Risk Management | F85: Daily loss limit | G85: COMPLETED | H85: 0.85 | J85: Live (ATIP-W24-RC1) | L85: max_daily_loss_value blocks BUYs; unmeasurable blocks | M85: Limit on PF-13; auto-halt | N85: orders/risk.py | O85: PF-13 | P85: 2026-09-24
A86: 85 | B86: 1 | C86: Foundation | D86: RK-08 | E86: Risk Management | F86: Drawdown limit | G86: COMPLETED | H86: 0.85 | J86: Live (ATIP-W24-RC1) | L86: max_drawdown_pct blocks BUYs; unmeasurable blocks | M86: Peak-to-trough on PF-13; auto-halt | N86: orders/risk.py | O86: PF-13 | P86: 2026-09-24
A87: 86 | B87: 1 | C87: Foundation | D87: DBS-03 | E87: Database | F87: Backups | G87: COMPLETED | H87: 0.85 | J87: Live (ATIP-W24-RC1) | L87: ops/backup.py: daily online SQLite backup (19:15) VERIFIED by integrity_check + key-table counts + sha256 (ops_backup); 7 daily + 4 weekly retention of its own files only; restore to a NEW file; python -m ops backup/restore/verify | M87: Off-machine copy of backups; restore drill | N87: ops/backup.py; docs/BACKUP_RESTORE.md | P87: 2026-09-25
A88: 87 | B88: 1 | C88: Foundation | D88: DP-06 | E88: Data Platform | F88: Corporate actions open items | G88: COMPLETED | H88: 0.85 | J88: Live (ATIP-W24-RC1) | L88: NSE CA calendar; reconciliation; volume re-base | M88: TVSMOTOR scheme; renamed symbols | N88: data/corporate_actions.py | P88: 2026-09-24
A89: 88 | B89: 1 | C89: Foundation | D89: TA-06 | E89: Technical Analysis | F89: Support/Resistance | G89: IMPLEMENTED BUT NOT VERIFIED | H89: 0.8 | I89: W21 | J89: Live (ATIP-W24-RC1) | K89: Independent QA | L89: W21: fractal pivots over 120 sessions, mean-anchored clusters, nearest confirmed support/resistance with touches and distance | M89: QA; optionally feed the Technical Score SR component | N89: data/technical_ext.py | P89: 2026-09-27
A90: 89 | B90: 1 | C90: Foundation | D90: DP-19 | E90: Data Platform | F90: Data quality layer | G90: COMPLETED | H90: 0.85 | J90: Live (ATIP-W24-RC1) | L90: data/quality.py 12 checks + DQS per session; data_quality table; post-market; alert | M90: DQS table; outlier and timestamp checks | N90: data/quality.py; pipeline/scheduler.py | O90: MON-01 | P90: 2026-09-24
A91: 90 | B91: 2 | C91: Quant Research (data, factors, backtesting) | D91: DBS-04 | E91: Database | F91: Schema migrations | G91: COMPLETED | H91: 0.8 | J91: Live (ATIP-W24-RC1) | L91: schema_migrations (version, checksum, applied_at, duration, status, rollback note); 0001 baseline, 0002 W8 tables, 0003 indexes, 0004 append-only audit triggers; drift detection; additive layer now runs once per process (W7-R8) | M91: Down-migration scripts beyond rollback notes (policy: restore pre-release backup) | N91: ops/migrations.py; db/schema.py | P91: 2026-09-25
A92: 91 | B92: 2 | C92: Quant Research (data, factors, backtesting) | D92: DP-01 | E92: Data Platform | F92: Live market data | G92: IN PROGRESS | H92: 0.6 | J92: — | K92: Development | L92: Index WebSocket 09:00-15:45 + quote cache; stock tick feed never run | M92: Stock-level live feed in production; failover | N92: data/dhan_ws.py; data/dhan.py | P92: 2026-09-24
A93: 92 | B93: 2 | C93: Quant Research (data, factors, backtesting) | D93: DP-03 | E93: Data Platform | F93: Intraday bars | G93: IMPLEMENTED BUT NOT VERIFIED | H93: 0.85 | I93: W21 | J93: Live (ATIP-W24-RC1) | K93: Independent QA | L93: W21: intraday_bars stores the 30-min job's 15-min bars (was discarded); 90-day retention | M93: QA; consider 5-min bars for session VWAP | N93: data/dhan.py; db/schema.py; db/purge.py | O93: DBS-04 | P93: 2026-09-27
A94: 93 | B94: 2 | C94: Quant Research (data, factors, backtesting) | D94: TA-03 | E94: Technical Analysis | F94: VWAP | G94: IMPLEMENTED BUT NOT VERIFIED | H94: 0.8 | I94: W21 | J94: Live (ATIP-W24-RC1) | K94: Independent QA; Owner: technical.vwap_in_score (changes scores) | L94: W21: vwap_20d, vwap_session (intraday bars), vwap_dev_pct in technical_ext; strategy feature vwap_dev_pct | M94: Owner: technical.vwap_in_score (changes scores); QA | N94: data/technical_ext.py; data/technical.py | O94: DP-03 | P94: 2026-09-27
A95: 94 | B95: 2 | C95: Quant Research (data, factors, backtesting) | D95: SC-12 | E95: Alpha/Factor Engine | F95: Technical Score VWAP input | G95: COMPLETED | H95: 0.75 | J95: Live (ATIP-W24-RC1) | L95: Implemented; VWAP weight dead | M95: Include VWAP | N95: data/technical.py | O95: TA-03 | P95: 2026-09-24
A96: 95 | B96: 2 | C96: Quant Research (data, factors, backtesting) | D96: TA-04 | E96: Technical Analysis | F96: Volume Profile | G96: IMPLEMENTED BUT NOT VERIFIED | H96: 0.8 | I96: W21 | J96: Live (ATIP-W24-RC1) | K96: Independent QA | L96: W21: volume profile POC/VAH/VAL over 20 sessions (intraday or daily basis) | M96: QA | N96: data/technical_ext.py | O96: DP-03 | P96: 2026-09-27
A97: 96 | B97: 2 | C97: Quant Research (data, factors, backtesting) | D97: TA-10 | E97: Technical Analysis | F97: Multi-timeframe analysis | G97: IMPLEMENTED BUT NOT VERIFIED | H97: 0.8 | I97: W21 | J97: Live (ATIP-W24-RC1) | K97: Independent QA | L97: W21: weekly RSI/trend, monthly trend, mtf_alignment -3..+3 | M97: QA | N97: data/technical_ext.py | O97: DP-03 | P97: 2026-09-27
A98: 97 | B98: 2 | C98: Quant Research (data, factors, backtesting) | D98: TA-12 | E98: Technical Analysis | F98: Full-history indicator panel | G98: IMPLEMENTED BUT NOT VERIFIED | H98: 0.7 | I98: W21 | J98: Live (ATIP-W24-RC1) | K98: Independent QA; Owner: When to run the indicator backfill | L98: W21: python -m data.technical --backfill N (tracked universe, resumable) | M98: Run the backfill (owner timing; copy first) | N98: data/technical.py | P98: 2026-09-27
A99: 98 | B99: 2 | C99: Quant Research (data, factors, backtesting) | D99: AF-03 | E99: Alpha/Factor Engine | F99: Factor panel persistence | G99: IMPLEMENTED BUT NOT VERIFIED | H99: 0.85 | I99: W22 | J99: Live (ATIP-W24-RC1) | K99: Independent QA | L99: W22: score_components stores every ATIP index's sub-components per symbol/date (weighted_score label capture; scores unchanged) | M99: QA | N99: scores/engine.py; scores/formulas.py | O99: TA-12 | P99: 2026-09-27
A100: 99 | B100: 2 | C100: Quant Research (data, factors, backtesting) | D100: AF-04 | E100: Alpha/Factor Engine | F100: Standalone factor families | G100: IMPLEMENTED BUT NOT VERIFIED | H100: 0.8 | I100: W22 | J100: Live (ATIP-W24-RC1) | K100: Independent QA | L100: W22: 11 standalone factors: mean reversion, trend, volume, recovery, risk (BRI) | M100: QA; research on full history | N100: quant/factors.py | O100: AF-03 | P100: 2026-09-27
A101: 100 | B101: 2 | C101: Quant Research (data, factors, backtesting) | D101: AF-02 | E101: Alpha/Factor Engine | F101: Normalisation contract | G101: IMPLEMENTED BUT NOT VERIFIED | H101: 0.85 | J101: Live (ATIP-W24-RC1) | K101: Independent QA | L101: W6 quant/normalize.py per-factor spec (winsorize/zscore/percentile/rank/minmax/sector/neutralize) -- tracker was stale | M101: QA | N101: quant/normalize.py | O101: AF-03 | P101: 2026-09-27
A102: 101 | B102: 2 | C102: Quant Research (data, factors, backtesting) | D102: AF-01 | E102: Alpha/Factor Engine | F102: Factor library/registry | G102: IMPLEMENTED BUT NOT VERIFIED | H102: 0.85 | J102: Live (ATIP-W24-RC1) | K102: Independent QA | L102: W6 registry quant_factor + factor sets + content-hash versioning (tracker was stale); W22 adds 11 factors | M102: QA | N102: quant/factors.py | O102: AF-03 | P102: 2026-09-27
A103: 102 | B103: 2 | C103: Quant Research (data, factors, backtesting) | D103: SC-18 | E103: Alpha/Factor Engine | F103: Formula registry/versioning | G103: IMPLEMENTED BUT NOT VERIFIED | H103: 0.85 | I103: W22 | J103: Live (ATIP-W24-RC1) | K103: Independent QA | L103: W22: formula_registry resolves each signal_log weights_hash to the full weight set + code version | M103: QA | N103: scores/formulas.py | O103: AF-01 | P103: 2026-09-27
A104: 103 | B104: 2 | C104: Quant Research (data, factors, backtesting) | D104: DBS-07 | E104: Database | F104: Research registry tables | G104: IMPLEMENTED BUT NOT VERIFIED | H104: 0.8 | I104: W22 | J104: Live (ATIP-W24-RC1) | K104: Independent QA | L104: W22: research_study + research_link registry, frozen on conclusion | M104: QA | N104: quant/studies.py | O104: DBS-04 | P104: 2026-09-27
A105: 104 | B105: 2 | C105: Quant Research (data, factors, backtesting) | D105: QR-01 | E105: Quant Research | F105: Information coefficient | G105: IMPLEMENTED BUT NOT VERIFIED | H105: 0.8 | I105: W22 | J105: Live (ATIP-W24-RC1) | K105: Independent QA | L105: W22: backfill_scores + research_report run IC for every factor | M105: Run full-history backfill + report | N105: quant/research.py | O105: AF-03 | P105: 2026-09-27
A106: 105 | B106: 2 | C106: Quant Research (data, factors, backtesting) | D106: QR-02 | E106: Quant Research | F106: IC decay / half-life | G106: IMPLEMENTED BUT NOT VERIFIED | H106: 0.8 | I106: W22 | J106: Live (ATIP-W24-RC1) | K106: Independent QA | L106: W22: IC decay 1/5/10/20 for every factor in research_report | M106: Run on full history | N106: quant/research.py | O106: QR-01 | P106: 2026-09-27
A107: 106 | B107: 2 | C107: Quant Research (data, factors, backtesting) | D107: QR-03 | E107: Quant Research | F107: Factor correlation/redundancy | G107: IMPLEMENTED BUT NOT VERIFIED | H107: 0.8 | I107: W22 | J107: Live (ATIP-W24-RC1) | K107: Independent QA | L107: W22: redundancy report (pairs |rho|>=0.7) in research_report | M107: Run on full history | N107: quant/research.py | O107: AF-03 | P107: 2026-09-27
A108: 107 | B108: 2 | C108: Quant Research (data, factors, backtesting) | D108: QR-04 | E108: Quant Research | F108: Statistical toolkit | G108: COMPLETED | H108: 0.75 | J108: Live (ATIP-W24-RC1) | L108: statarb (OLS, ADF, Engle-Granger, half-life, z) + normalize + volatility estimators | M108: Validate | N108: quant/statarb.py; quant/normalize.py; quant/volatility.py | O108: AF-03 | P108: 2026-09-25
A109: 108 | B109: 2 | C109: Quant Research (data, factors, backtesting) | D109: AF-08 | E109: Alpha/Factor Engine | F109: Factor approval gate | G109: IMPLEMENTED BUT NOT VERIFIED | H109: 0.8 | I109: W22 | J109: Live (ATIP-W24-RC1) | K109: Independent QA; Owner: quant.require_approved_factors | L109: W22: evidence-based approval gate, decision history, lifecycle enforcement behind quant.require_approved_factors | M109: Owner: enable after review | N109: quant/approval.py; strategy_engine/lifecycle.py | O109: QR-01; QR-03 | P109: 2026-09-27
A110: 109 | B110: 2 | C110: Quant Research (data, factors, backtesting) | D110: BT-16 | E110: Backtesting | F110: Dated equity curve / run records | G110: COMPLETED | H110: 0.85 | J110: Live (ATIP-W24-RC1) | L110: backtest_run snapshot+hash, code version, data fingerprint; trades/equity/drawdowns tables | M110: Dated trades + equity curve + run table | N110: backtest/store.py; db/schema.py | P110: 2026-09-24
A111: 110 | B111: 2 | C111: Quant Research (data, factors, backtesting) | D111: BT-08 | E111: Backtesting | F111: Portfolio-level backtest | G111: COMPLETED | H111: 0.85 | J111: Live (ATIP-W24-RC1) | L111: Portfolio engine: cash, positions, sizing (W1 size_position), exposure, dated equity | M111: Portfolio simulator | N111: backtest/engine.py | O111: BT-16 | P111: 2026-09-24
A112: 111 | B112: 2 | C112: Quant Research (data, factors, backtesting) | D112: BT-09 | E112: Backtesting | F112: Drawdown analysis | G112: COMPLETED | H112: 0.9 | J112: Live (ATIP-W24-RC1) | L112: Drawdown series, max DD, episodes with duration/recovery on dated equity | M112: Compute on equity curve | N112: backtest/metrics.py | O112: BT-16 | P112: 2026-09-24
A113: 112 | B113: 2 | C113: Quant Research (data, factors, backtesting) | D113: BT-11 | E113: Backtesting | F113: Sharpe/Sortino/CAGR/Calmar | G113: COMPLETED | H113: 0.9 | J113: Live (ATIP-W24-RC1) | L113: Return, CAGR, vol, Sharpe, Sortino, Calmar, trade stats; conventions documented | M113: Implement | N113: backtest/metrics.py | O113: BT-16 | P113: 2026-09-24
A114: 113 | B114: 2 | C114: Quant Research (data, factors, backtesting) | D114: BT-12 | E114: Backtesting | F114: VaR/CVaR in backtest | G114: IMPLEMENTED BUT NOT VERIFIED | H114: 0.85 | I114: W23 | J114: Live (ATIP-W24-RC1) | K114: Independent QA | L114: W23: historical VaR/CVaR 95/99, parametric VaR, skew, kurtosis in every backtest's metrics | M114: QA | N114: backtest/metrics.py | O114: BT-16 | P114: 2026-09-27
A115: 114 | B115: 2 | C115: Quant Research (data, factors, backtesting) | D115: BT-05 | E115: Backtesting | F115: Itemised costs | G115: COMPLETED | H115: 0.85 | J115: Live (ATIP-W24-RC1) | L115: Itemised NSE cost model (delivery/intraday/flat/zero), central config | M115: Indian cost model shared by backtest and paper | N115: backtest/costs.py; backtest/config.py | P115: 2026-09-24
A116: 115 | B116: 2 | C116: Quant Research (data, factors, backtesting) | D116: BT-06 | E116: Backtesting | F116: Slippage in backtest | G116: COMPLETED | H116: 0.9 | J116: Live (ATIP-W24-RC1) | L116: none / fixed / pct slippage, default = paper broker 5 bps | M116: Shared slippage model | N116: backtest/slippage.py | O116: BT-05 | P116: 2026-09-24
A117: 116 | B117: 2 | C117: Quant Research (data, factors, backtesting) | D117: BT-07 | E117: Backtesting | F117: Liquidity constraints | G117: COMPLETED | H117: 0.85 | J117: Live (ATIP-W24-RC1) | L117: Volume participation cap/reject + prior-bar turnover floor | M117: All engines | N117: backtest/liquidity.py | P117: 2026-09-24
A118: 117 | B118: 2 | C118: Quant Research (data, factors, backtesting) | D118: DP-18 | E118: Data Platform | F118: Survivorship-free universe | G118: COMPLETED | H118: 0.8 | J118: Live (ATIP-W24-RC1) | L118: Current NIFTY 500 download | M118: Store constituent history | N118: data/index_constituents.py | P118: 2026-09-24
A119: 118 | B119: 2 | C119: Quant Research (data, factors, backtesting) | D119: BT-15 | E119: Backtesting | F119: Bias controls | G119: COMPLETED | H119: 0.8 | J119: Live (ATIP-W24-RC1) | L119: Point-in-time view + LookAheadError, next-open fills, data/timestamp validation, survivorship flag | M119: Systematic checks | N119: backtest/data.py; backtest/engine.py | O119: DP-18 | P119: 2026-09-24
A120: 119 | B120: 2 | C120: Quant Research (data, factors, backtesting) | D120: BT-03 | E120: Backtesting | F120: In/out-of-sample | G120: COMPLETED | H120: 0.85 | J120: Live (ATIP-W24-RC1) | L120: Ordered non-overlapping research/validation/test; test needs allow_test; re-test flagged | M120: Formal splits | N120: backtest/periods.py; backtest/service.py | O120: BT-16 | P120: 2026-09-24
A121: 120 | B121: 2 | C121: Quant Research (data, factors, backtesting) | D121: BT-02 | E121: Backtesting | F121: Walk-forward | G121: COMPLETED | H121: 0.8 | J121: Live (ATIP-W24-RC1) | L121: Rolling windows, candidate selection on validation, stitched OOS; no optimiser | M121: Implement | N121: backtest/walkforward.py | O121: BT-03 | P121: 2026-09-24
A122: 121 | B122: 2 | C122: Quant Research (data, factors, backtesting) | D122: BT-13 | E122: Backtesting | F122: Monte Carlo | G122: COMPLETED | H122: 0.85 | J122: Live (ATIP-W24-RC1) | L122: Seeded trade shuffle + return bootstrap; percentiles, P(loss), disclaimer | M122: Implement | N122: backtest/montecarlo.py | O122: BT-16 | P122: 2026-09-24
A123: 122 | B123: 2 | C123: Quant Research (data, factors, backtesting) | D123: BT-04 | E123: Backtesting | F123: Parameter optimisation | G123: IMPLEMENTED BUT NOT VERIFIED | H123: 0.8 | I123: W23 | J123: Live (ATIP-W24-RC1) | K123: Independent QA | L123: W23: grid / random / adaptive optimiser with trial runs, test-window refusal, Deflated Sharpe + overfit warning | M123: QA; optional true Bayesian search | N123: backtest/optimize.py | O123: BT-02 | P123: 2026-09-27
A124: 123 | B124: 2 | C124: Quant Research (data, factors, backtesting) | D124: QR-11 | E124: Quant Research | F124: Parameter sensitivity | G124: IMPLEMENTED BUT NOT VERIFIED | H124: 0.8 | I124: W23 | J124: Live (ATIP-W24-RC1) | K124: Independent QA | L124: W23: one-at-a-time sensitivity curves, stability, knife-edge flags, 2-D heat map | M124: QA | N124: backtest/sensitivity.py | O124: BT-04 | P124: 2026-09-27
A125: 124 | B125: 2 | C125: Quant Research (data, factors, backtesting) | D125: BT-14 | E125: Backtesting | F125: Robustness | G125: IMPLEMENTED BUT NOT VERIFIED | H125: 0.8 | I125: W23 | J125: Live (ATIP-W24-RC1) | K125: Independent QA | L125: W23: robustness battery (costs x2, slippage x3, universe halves, period halves, regimes, Monte Carlo) with verdict | M125: QA | N125: backtest/robustness.py | O125: BT-02 | P125: 2026-09-27
A126: 125 | B126: 2 | C126: Quant Research (data, factors, backtesting) | D126: QR-12 | E126: Quant Research | F126: Reproducibility / experiment tracking | G126: IMPLEMENTED BUT NOT VERIFIED | H126: 0.8 | J126: Live (ATIP-W24-RC1) | K126: Independent QA | L126: W6 experiments + W22 studies linking experiments/backtests/research | M126: QA | N126: quant/experiments.py; quant/studies.py | O126: DBS-07 | P126: 2026-09-27
A127: 126 | B127: 2 | C127: Quant Research (data, factors, backtesting) | D127: QR-07 | E127: Quant Research | F127: Momentum/trend research | G127: IMPLEMENTED BUT NOT VERIFIED | H127: 0.7 | I127: W23 | J127: Live (ATIP-W24-RC1) | K127: Independent QA | L127: W23: momentum breakout strategy + end-to-end study (optimise/validate/sensitivity/robustness/test) | M127: Run full-universe study; review | N127: backtest/strategies.py; backtest/study.py | O127: BT-02 | P127: 2026-09-27
A128: 127 | B128: 2 | C128: Quant Research (data, factors, backtesting) | D128: QR-08 | E128: Quant Research | F128: Mean-reversion research | G128: IMPLEMENTED BUT NOT VERIFIED | H128: 0.7 | I128: W23 | J128: Live (ATIP-W24-RC1) | K128: Independent QA | L128: W23: RSI(2) mean-reversion strategy + study; 12-stock smoke: REJECTED out of sample | M128: Run full-universe study; review | N128: backtest/strategies.py; backtest/study.py | O128: BT-02 | P128: 2026-09-27
A129: 128 | B129: 2 | C129: Quant Research (data, factors, backtesting) | D129: QR-13 | E129: Quant Research | F129: Signal outcome research by regime | G129: COMPLETED | H129: 0.7 | J129: Live (ATIP-W24-RC1) | L129: success_report keyed on signal/threshold | M129: Add regime/ACS buckets | N129: scores/signal_log.py | O129: ML-05 | P129: 2026-09-24
A130: 129 | B130: 2 | C130: Quant Research (data, factors, backtesting) | D130: TA-09 | E130: Technical Analysis | F130: Beta 3y / rolling 60 | G130: IMPLEMENTED BUT NOT VERIFIED | H130: 0.7 | I130: W21 | J130: Live (ATIP-W24-RC1) | K130: Independent QA; Owner: prices_daily retention >= 1,100 days | L130: W21: beta_60, beta_downside, beta_long (>=500 sessions) | M130: Owner: prices_daily retention >= 1,100 days for a 3-year beta | N130: data/technical_ext.py | O130: TA-12 | P130: 2026-09-27
A131: 130 | B131: 2 | C131: Quant Research (data, factors, backtesting) | D131: SC-16 | E131: Alpha/Factor Engine | F131: Beta Risk Index | G131: IMPLEMENTED BUT NOT VERIFIED | H131: 0.75 | I131: W21 | J131: Live (ATIP-W24-RC1) | K131: Independent QA | L131: W21: Beta Risk Index 0-100 (level, downside, instability); strategy feature bri | M131: QA; decide if it joins a composite | N131: data/technical_ext.py | O131: TA-09 | P131: 2026-09-27
A132: 131 | B132: 2 | C132: Quant Research (data, factors, backtesting) | D132: TA-11 | E132: Technical Analysis | F132: Extended indicator catalogue | G132: IMPLEMENTED BUT NOT VERIFIED | H132: 0.8 | I132: W21 | J132: Live (ATIP-W24-RC1) | K132: Independent QA | L132: W21: Supertrend, Ichimoku, Keltner, Donchian, MFI, CMF, ROC, Aroon, PSAR; stoch/Williams %R/CCI now computed | M132: QA | N132: data/technical_ext.py; data/technical.py | O132: TA-12 | P132: 2026-09-27
A133: 132 | B133: 2 | C133: Quant Research (data, factors, backtesting) | D133: DP-08 | E133: Data Platform | F133: Derivatives data | G133: YET TO START | H133: 0 | J133: — | K133: Owner: Choose a derivatives data source | L133: None | M133: NSE F&O bhavcopy + option chain store | N133: — | O133: DBS-04 | P133: 2026-09-24
A134: 133 | B134: 2 | C134: Quant Research (data, factors, backtesting) | D134: SC-06 | E134: Alpha/Factor Engine | F134: MSI | G134: IN PROGRESS | H134: 0.55 | J134: — | K134: Development | L134: Options/PCR frozen; news rule-based | M134: Real PCR; AI news later | N134: scores/engine.py | O134: DP-08 | P134: 2026-09-24
A135: 134 | B135: 2 | C135: Quant Research (data, factors, backtesting) | D135: DP-10 | E135: Data Platform | F135: FII/DII history | G135: COMPLETED | H135: 0.8 | J135: Live (ATIP-W24-RC1) | L135: Session flows; only 7 sessions history | M135: Historical backfill source | N135: data/bhavcopy.py | P135: 2026-09-24
A136: 135 | B136: 2 | C136: Quant Research (data, factors, backtesting) | D136: DP-11 | E136: Data Platform | F136: GIFT Nifty | G136: IMPLEMENTED BUT NOT VERIFIED | H136: 0.75 | I136: W21 | J136: Live (ATIP-W24-RC1) | K136: Independent QA | L136: W21: daily GIFTNIFTY close from index_levels into prices_daily | M136: Pre-open panel (DB-04) | N136: data/market_series.py | P136: 2026-09-27
A137: 136 | B137: 2 | C137: Quant Research (data, factors, backtesting) | D137: DB-04 | E137: Dashboard | F137: GIFT Nifty panel | G137: IN PROGRESS | H137: 0.6 | J137: — | K137: Development | L137: In index strip | M137: Dedicated pre-open view | N137: dashboard/server.py | O137: DP-11 | P137: 2026-09-24
A138: 137 | B138: 2 | C138: Quant Research (data, factors, backtesting) | D138: DP-12 | E138: Data Platform | F138: Global markets | G138: IN PROGRESS | H138: 0.7 | J138: — | K138: Development | L138: 13 yfinance tickers | M138: Bond yields; history depth | N138: data/markets.py | P138: 2026-09-24
A139: 138 | B139: 2 | C139: Quant Research (data, factors, backtesting) | D139: DP-13 | E139: Data Platform | F139: Sector data | G139: IMPLEMENTED BUT NOT VERIFIED | H139: 0.8 | I139: W21 | J139: Live (ATIP-W24-RC1) | K139: Independent QA | L139: W21: 8 sector index series in the daily Dhan sync + sector_breadth table | M139: Run --backfill-sectors; QA | N139: data/market_series.py; data/dhan.py | P139: 2026-09-27
A140: 139 | B140: 2 | C140: Quant Research (data, factors, backtesting) | D140: DP-16 | E140: Data Platform | F140: Institutional data | G140: IN PROGRESS | H140: 0.25 | J140: — | K140: Development | L140: Bulk/block only | M140: Promoter/SAST/PIT/MF feeds | N140: data/bhavcopy.py | P140: 2026-09-24
A141: 140 | B141: 2 | C141: Quant Research (data, factors, backtesting) | D141: SC-14 | E141: Alpha/Factor Engine | F141: Institutional Score | G141: IN PROGRESS | H141: 0.4 | J141: — | K141: Development | L141: FII + bulk only | M141: Add MF/promoter/insider | N141: scores/engine.py | O141: DP-16 | P141: 2026-09-24
A142: 141 | B142: 2 | C142: Quant Research (data, factors, backtesting) | D142: AD-03 | E142: Alternative Data | F142: Bulk/block deal signal | G142: IN PROGRESS | H142: 0.4 | J142: — | K142: Development | L142: Feeds INS | M142: Validate with IC | N142: data/bhavcopy.py | O142: DP-16 | P142: 2026-09-24
A143: 142 | B143: 3 | C143: Strategy Engine | D143: SG-04 | E143: Signal Engine | F143: Rich decision states | G143: COMPLETED | H143: 0.8 | J143: Live (ATIP-W24-RC1) | L143: Decision states BUY/ADD/HOLD/REDUCE/EXIT/SELL/NO_ACTION/BLOCKED_BY_RISK with reasons; PositionIntent | M143: Extended states + stored reasons | N143: strategy_engine/decisions.py | O143: BT-02 | P143: 2026-09-24
A144: 143 | B144: 3 | C144: Strategy Engine | D144: SG-01 | E144: Signal Engine | F144: SELL calibration | G144: COMPLETED | H144: 0.7 | J144: Live (ATIP-W24-RC1) | L144: SELL never fired | M144: Backtest-based SELL thresholds | N144: scores/engine.py | O144: BT-02 | P144: 2026-09-24
A145: 144 | B145: 3 | C145: Strategy Engine | D145: SE-01 | E145: Strategy Engine | F145: Strategy library | G145: COMPLETED | H145: 0.85 | J145: Live (ATIP-W24-RC1) | L145: Versioned JSON definitions + DB registry (id, name, description, category, version, status, owner, created/updated, priority, weight); VERSION/LIFECYCLE events; 9 library strategies | M145: Strategy interface + registry | N145: strategy_engine/definition.py; registry.py | O145: BT-16 | P145: 2026-09-24
A146: 145 | B146: 3 | C146: Strategy Engine | D146: SE-02 | E146: Strategy Engine | F146: Strategy parameters | G146: COMPLETED | H146: 0.85 | J146: Live (ATIP-W24-RC1) | L146: ParamSpec name/type/default/min/max/allowed/required/description; validated on resolve; stored per version in strategy_parameter | M146: Param store per strategy with versions | N146: strategy_engine/params.py; registry.py | O146: SE-01 | P146: 2026-09-24
...

Sheet Built - Needs QA
A1: Seq | B1: Phase Name | C1: ID | D1: Module | E1: Feature | F1: Completion % | G1: Wave | H1: Current Implementation | I1: Next Action / Missing Work | J1: Needs
A2: 88 | B2: Foundation | C2: TA-06 | D2: Technical Analysis | E2: Support/Resistance | F2: 0.8 | G2: W21 | H2: W21: fractal pivots over 120 sessions, mean-anchored clusters, nearest confirmed support/resistance with touches and distance | I2: QA; optionally feed the Technical Score SR component | J2: Independent QA
A3: 92 | B3: Quant Research (data, factors, backtesting) | C3: DP-03 | D3: Data Platform | E3: Intraday bars | F3: 0.85 | G3: W21 | H3: W21: intraday_bars stores the 30-min job's 15-min bars (was discarded); 90-day retention | I3: QA; consider 5-min bars for session VWAP | J3: Independent QA
A4: 93 | B4: Quant Research (data, factors, backtesting) | C4: TA-03 | D4: Technical Analysis | E4: VWAP | F4: 0.8 | G4: W21 | H4: W21: vwap_20d, vwap_session (intraday bars), vwap_dev_pct in technical_ext; strategy feature vwap_dev_pct | I4: Owner: technical.vwap_in_score (changes scores); QA | J4: Independent QA; Owner: technical.vwap_in_score (changes scores)
A5: 95 | B5: Quant Research (data, factors, backtesting) | C5: TA-04 | D5: Technical Analysis | E5: Volume Profile | F5: 0.8 | G5: W21 | H5: W21: volume profile POC/VAH/VAL over 20 sessions (intraday or daily basis) | I5: QA | J5: Independent QA
A6: 96 | B6: Quant Research (data, factors, backtesting) | C6: TA-10 | D6: Technical Analysis | E6: Multi-timeframe analysis | F6: 0.8 | G6: W21 | H6: W21: weekly RSI/trend, monthly trend, mtf_alignment -3..+3 | I6: QA | J6: Independent QA
A7: 97 | B7: Quant Research (data, factors, backtesting) | C7: TA-12 | D7: Technical Analysis | E7: Full-history indicator panel | F7: 0.7 | G7: W21 | H7: W21: python -m data.technical --backfill N (tracked universe, resumable) | I7: Run the backfill (owner timing; copy first) | J7: Independent QA; Owner: When to run the indicator backfill
A8: 98 | B8: Quant Research (data, factors, backtesting) | C8: AF-03 | D8: Alpha/Factor Engine | E8: Factor panel persistence | F8: 0.85 | G8: W22 | H8: W22: score_components stores every ATIP index's sub-components per symbol/date (weighted_score label capture; scores unchanged) | I8: QA | J8: Independent QA
A9: 99 | B9: Quant Research (data, factors, backtesting) | C9: AF-04 | D9: Alpha/Factor Engine | E9: Standalone factor families | F9: 0.8 | G9: W22 | H9: W22: 11 standalone factors: mean reversion, trend, volume, recovery, risk (BRI) | I9: QA; research on full history | J9: Independent QA
A10: 100 | B10: Quant Research (data, factors, backtesting) | C10: AF-02 | D10: Alpha/Factor Engine | E10: Normalisation contract | F10: 0.85 | H10: W6 quant/normalize.py per-factor spec (winsorize/zscore/percentile/rank/minmax/sector/neutralize) -- tracker was stale | I10: QA | J10: Independent QA
A11: 101 | B11: Quant Research (data, factors, backtesting) | C11: AF-01 | D11: Alpha/Factor Engine | E11: Factor library/registry | F11: 0.85 | H11: W6 registry quant_factor + factor sets + content-hash versioning (tracker was stale); W22 adds 11 factors | I11: QA | J11: Independent QA
A12: 102 | B12: Quant Research (data, factors, backtesting) | C12: SC-18 | D12: Alpha/Factor Engine | E12: Formula registry/versioning | F12: 0.85 | G12: W22 | H12: W22: formula_registry resolves each signal_log weights_hash to the full weight set + code version | I12: QA | J12: Independent QA
A13: 103 | B13: Quant Research (data, factors, backtesting) | C13: DBS-07 | D13: Database | E13: Research registry tables | F13: 0.8 | G13: W22 | H13: W22: research_study + research_link registry, frozen on conclusion | I13: QA | J13: Independent QA
A14: 104 | B14: Quant Research (data, factors, backtesting) | C14: QR-01 | D14: Quant Research | E14: Information coefficient | F14: 0.8 | G14: W22 | H14: W22: backfill_scores + research_report run IC for every factor | I14: Run full-history backfill + report | J14: Independent QA
A15: 105 | B15: Quant Research (data, factors, backtesting) | C15: QR-02 | D15: Quant Research | E15: IC decay / half-life | F15: 0.8 | G15: W22 | H15: W22: IC decay 1/5/10/20 for every factor in research_report | I15: Run on full history | J15: Independent QA
A16: 106 | B16: Quant Research (data, factors, backtesting) | C16: QR-03 | D16: Quant Research | E16: Factor correlation/redundancy | F16: 0.8 | G16: W22 | H16: W22: redundancy report (pairs |rho|>=0.7) in research_report | I16: Run on full history | J16: Independent QA
A17: 108 | B17: Quant Research (data, factors, backtesting) | C17: AF-08 | D17: Alpha/Factor Engine | E17: Factor approval gate | F17: 0.8 | G17: W22 | H17: W22: evidence-based approval gate, decision history, lifecycle enforcement behind quant.require_approved_factors | I17: Owner: enable after review | J17: Independent QA; Owner: quant.require_approved_factors
A18: 113 | B18: Quant Research (data, factors, backtesting) | C18: BT-12 | D18: Backtesting | E18: VaR/CVaR in backtest | F18: 0.85 | G18: W23 | H18: W23: historical VaR/CVaR 95/99, parametric VaR, skew, kurtosis in every backtest's metrics | I18: QA | J18: Independent QA
A19: 122 | B19: Quant Research (data, factors, backtesting) | C19: BT-04 | D19: Backtesting | E19: Parameter optimisation | F19: 0.8 | G19: W23 | H19: W23: grid / random / adaptive optimiser with trial runs, test-window refusal, Deflated Sharpe + overfit warning | I19: QA; optional true Bayesian search | J19: Independent QA
A20: 123 | B20: Quant Research (data, factors, backtesting) | C20: QR-11 | D20: Quant Research | E20: Parameter sensitivity | F20: 0.8 | G20: W23 | H20: W23: one-at-a-time sensitivity curves, stability, knife-edge flags, 2-D heat map | I20: QA | J20: Independent QA
A21: 124 | B21: Quant Research (data, factors, backtesting) | C21: BT-14 | D21: Backtesting | E21: Robustness | F21: 0.8 | G21: W23 | H21: W23: robustness battery (costs x2, slippage x3, universe halves, period halves, regimes, Monte Carlo) with verdict | I21: QA | J21: Independent QA
A22: 125 | B22: Quant Research (data, factors, backtesting) | C22: QR-12 | D22: Quant Research | E22: Reproducibility / experiment tracking | F22: 0.8 | H22: W6 experiments + W22 studies linking experiments/backtests/research | I22: QA | J22: Independent QA
A23: 126 | B23: Quant Research (data, factors, backtesting) | C23: QR-07 | D23: Quant Research | E23: Momentum/trend research | F23: 0.7 | G23: W23 | H23: W23: momentum breakout strategy + end-to-end study (optimise/validate/sensitivity/robustness/test) | I23: Run full-universe study; review | J23: Independent QA
A24: 127 | B24: Quant Research (data, factors, backtesting) | C24: QR-08 | D24: Quant Research | E24: Mean-reversion research | F24: 0.7 | G24: W23 | H24: W23: RSI(2) mean-reversion strategy + study; 12-stock smoke: REJECTED out of sample | I24: Run full-universe study; review | J24: Independent QA
A25: 129 | B25: Quant Research (data, factors, backtesting) | C25: TA-09 | D25: Technical Analysis | E25: Beta 3y / rolling 60 | F25: 0.7 | G25: W21 | H25: W21: beta_60, beta_downside, beta_long (>=500 sessions) | I25: Owner: prices_daily retention >= 1,100 days for a 3-year beta | J25: Independent QA; Owner: prices_daily retention >= 1,100 days
A26: 130 | B26: Quant Research (data, factors, backtesting) | C26: SC-16 | D26: Alpha/Factor Engine | E26: Beta Risk Index | F26: 0.75 | G26: W21 | H26: W21: Beta Risk Index 0-100 (level, downside, instability); strategy feature bri | I26: QA; decide if it joins a composite | J26: Independent QA
A27: 131 | B27: Quant Research (data, factors, backtesting) | C27: TA-11 | D27: Technical Analysis | E27: Extended indicator catalogue | F27: 0.8 | G27: W21 | H27: W21: Supertrend, Ichimoku, Keltner, Donchian, MFI, CMF, ROC, Aroon, PSAR; stoch/Williams %R/CCI now computed | I27: QA | J27: Independent QA
A28: 135 | B28: Quant Research (data, factors, backtesting) | C28: DP-11 | D28: Data Platform | E28: GIFT Nifty | F28: 0.75 | G28: W21 | H28: W21: daily GIFTNIFTY close from index_levels into prices_daily | I28: Pre-open panel (DB-04) | J28: Independent QA
A29: 138 | B29: Quant Research (data, factors, backtesting) | C29: DP-13 | D29: Data Platform | E29: Sector data | F29: 0.8 | G29: W21 | H29: W21: 8 sector index series in the daily Dhan sync + sector_breadth table | I29: Run --backfill-sectors; QA | J29: Independent QA
A30: 157 | B30: AI/ML | C30: ML-07 | D30: AI/ML | E30: Feature selection | F30: 0.8 | G30: W24 | H30: W24: importance-stability selection -> new feature-set version | I30: QA | J30: Independent QA
A31: 158 | B31: AI/ML | C31: ML-08 | D31: AI/ML | E31: Model validation | F31: 0.85 | G31: W24 | H31: W24: purged expanding walk-forward reports vs baselines, IC, calibration, verdict | I31: QA | J31: Independent QA
A32: 159 | B32: AI/ML | C32: ML-01 | D32: AI/ML | E32: Supervised ML | F32: 0.8 | G32: W24 | H32: W24: native numpy GBM + random forest; bootstrap trains + validates first models (TRAINED, not ACTIVE); real-data smoke: NO_EDGE on 5-day direction | I32: Richer features / labels; full-universe validation | J32: Independent QA
A33: 161 | B33: AI/ML | C33: ML-11 | D33: AI/ML | E33: Ensemble models | F33: 0.8 | G33: W24 | H33: W24: ensemble model type blended by held-out loss | I33: QA | J33: Independent QA
A34: 162 | B34: AI/ML | C34: ML-09 | D34: AI/ML | E34: Model monitoring/drift | F34: 0.8 | G34: W24 | H34: W24: drift (PSI share) + realised decay alerts, ml_health_check, monitor rule | I34: QA | J34: Independent QA
... A62: 277 | B62: Wealth track (Waves 11-20) | C62: REL-001 | D62: Wealth | E62: Wealth production hardening | F62: 0.8 | G62: W20 | H62: W20: Migration 0005, /health/wealth, monitor, backup, docs, RC | I62: Independent testing (ChatGPT) + UAT; merge after authorization | J62: Independent QA

Sheet In Progress
A1: Seq | B1: Phase Name | C1: ID | D1: Module | E1: Feature | F1: Completion % | G1: Wave | H1: Current Implementation | I1: Next Action / Missing Work | J1: Needs
A2: 74 | B2: Foundation | C2: DP-15 | D2: Data Platform | E2: Fundamentals | F2: 0.3 | H2: Screener.in fetcher; ingestion disabled | I2: Your decision; enable; quarterly store; no 50.0 default | J2: Owner: Enable fundamentals ingestion (Screener.in)
A3: 75 | B3: Foundation | C3: SC-13 | D3: Alpha/Factor Engine | E3: Fundamental Score | F3: 0.2 | H3: Default 50 when unparsed | I3: Implement FS formula on real data | J3: Development
A4: 76 | B4: Foundation | C4: SC-02 | D4: Alpha/Factor Engine | E4: SPI | F4: 0.3 | H4: =fundamental_score (double-weighted) | I4: Implement SPI formula separately from FS | J4: Development
A5: 91 | B5: Quant Research (data, factors, backtesting) | C5: DP-01 | D5: Data Platform | E5: Live market data | F5: 0.6 | H5: Index WebSocket 09:00-15:45 + quote cache; stock tick feed never run | I5: Stock-level live feed in production; failover | J5: Development
A6: 133 | B6: Quant Research (data, factors, backtesting) | C6: SC-06 | D6: Alpha/Factor Engine | E6: MSI | F6: 0.55 | H6: Options/PCR frozen; news rule-based | I6: Real PCR; AI news later | J6: Development
A7: 136 | B7: Quant Research (data, factors, backtesting) | C7: DB-04 | D7: Dashboard | E7: GIFT Nifty panel | F7: 0.6 | H7: In index strip | I7: Dedicated pre-open view | J7: Development
A8: 137 | B8: Quant Research (data, factors, backtesting) | C8: DP-12 | D8: Data Platform | E8: Global markets | F8: 0.7 | H8: 13 yfinance tickers | I8: Bond yields; history depth | J8: Development
A9: 139 | B9: Quant Research (data, factors, backtesting) | C9: DP-16 | D9: Data Platform | E9: Institutional data | F9: 0.25 | H9: Bulk/block only | I9: Promoter/SAST/PIT/MF feeds | J9: Development
A10: 140 | B10: Quant Research (data, factors, backtesting) | C10: SC-14 | D10: Alpha/Factor Engine | E10: Institutional Score | F10: 0.4 | H10: FII + bulk only | I10: Add MF/promoter/insider | J10: Development
A11: 141 | B11: Quant Research (data, factors, backtesting) | C11: AD-03 | D11: Alternative Data | E11: Bulk/block deal signal | F11: 0.4 | H11: Feeds INS | I11: Validate with IC | J11: Development
A12: 153 | B12: Strategy Engine | C12: SG-08 | D12: Signal Engine | E12: Intraday scans | F12: 0.6 | H12: Scheduled 12:30 and 14:45 | I12: Use stored intraday bars | J12: Development
A13: 154 | B13: Strategy Engine | C13: DB-11 | D13: Dashboard | E13: Crash Risk + Top 25 SPI/MSI lists | F13: 0.4 | H13: CRI per-stock column only | I13: Dedicated lists | J13: Development
A14: 155 | B14: Strategy Engine | C14: DB-16 | D14: Dashboard | E14: Strategy performance panel | F14: 0.3 | H14: /strategies list shows latest signals; per-strategy P&L from W4 fills on /trading | I14: Performance panel | J14: Development
A15: 167 | B15: AI/ML | C15: SE-05 | D15: Strategy Engine | E15: AI-driven strategies | F15: 0.6 | H15: ml_* strategy features (point in time, out of sample); ml_direction / atip_ml_blend (DRAFT); W4 risk check ml_model_active blocks signals of non-ACTIVE models | I15: Activate once a model is ACTIVE | J15: Owner: Activate a model (after evidence)
A16: 168 | B16: AI/ML | C16: NS-02 | D16: News/Sentiment | E16: News classification | F16: 0.3 | H16: Claude classifier coded; key unset | I16: Set key; taxonomy; cost cap | J16: Owner: Provide a working Anthropic API key (current key 401)
... A57: 265 | B57: Production hardening | C57: OPS-11 | D57: Deployment/Ops | E57: Release management & deployment | F57: 0.8 | H57: Tag ATIP-W9-RC2; ops/release.py preflight/manifest/postcheck/record; deploy/deploy_release.ps1 + rollback_release.ps1 (dry-run default); requirements.lock.txt; release docs | I57: Authorized deployment + first executed rollback drill | J57: Development
A58: 275 | B58: Wealth track (Waves 11-20) | C58: QA-001 | D58: Wealth | E58: Wealth QA / security / performance | F58: 0.6 | G58: W18 | H58: W18: 70-test suite, security review (S1/S2 fixed), performance | I58: Independent testing (ChatGPT) + UAT; merge after authorization | J58: Development
A59: 276 | B59: Wealth track (Waves 11-20) | C59: UAT-001 | D59: Wealth | E59: Beta / UAT | F59: 0.6 | G59: W19 | H59: W19: Personas, persona view, feedback, UAT plan | I59: Independent testing (ChatGPT) + UAT; merge after authorization | J59: Development

Sheet Yet To Start
A1: Seq | B1: Phase Name | C1: ID | D1: Module | E1: Feature | F1: Completion % | G1: Wave | H1: Current Implementation | I1: Next Action / Missing Work | J1: Needs
A2: 132 | B2: Quant Research (data, factors, backtesting) | C2: DP-08 | D2: Data Platform | E2: Derivatives data | F2: 0 | H2: None | I2: NSE F&O bhavcopy + option chain store | J2: Owner: Choose a derivatives data source
A3: 170 | B3: AI/ML | C3: NS-05 | D3: News/Sentiment | E3: Novelty/decay/source weighting | F3: 0.05 | H3: None | I3: Implement | J3: Development
A4: 173 | B4: AI/ML | C4: NS-06 | D4: News/Sentiment | E4: Earnings call / announcement NLP | F4: 0 | H4: None | I4: Implement | J4: Development
A5: 174 | B5: AI/ML | C5: ML-02 | D5: AI/ML | E5: Deep learning | F5: 0 | H5: None | I5: Only if validated benefit | J5: Development
A6: 175 | B6: AI/ML | C6: ML-04 | D6: AI/ML | E6: Reinforcement learning | F6: 0 | H6: None | I6: Low priority | J6: Development
A7: 205 | B7: Advanced Quant | C7: DP-04 | D7: Data Platform | E7: Tick data | F7: 0.05 | H7: live_ticks exists; 0 rows | I7: Tick ingestion + storage | J7: Development
A8: 206 | B8: Advanced Quant | C8: DP-05 | D8: Data Platform | E8: Order book / depth | F8: 0.05 | H8: FULL feed type defined (CLI only) | I8: Depth capture + schema | J8: Development
A9: 214 | B9: Advanced Quant | C9: EX-11 | D9: Execution | E9: Execution algos | F9: 0 | H9: None | I9: Implement | J9: Development
A10: 215 | B10: Advanced Quant | C10: EX-12 | D10: Execution | E10: Market impact model | F10: 0 | H10: None | I10: Implement | J10: Development
A11: 216 | B11: Advanced Quant | C11: EX-15 | D11: Execution | E11: Latency telemetry | F11: 0 | H11: None | I11: Instrument data and order paths | J11: Development
A12: 217 | B12: Advanced Quant | C12: EX-16 | D12: Execution | E12: Event-driven OMS | F12: 0.1 | H12: Synchronous calls | I12: Implement | J12: Development
A13: 218 | B13: Advanced Quant | C13: BT-17 | D13: Backtesting | E13: Event-driven backtester | F13: 0 | H13: Bar loops only | I13: Implement | J13: Development
... A33: 232 | B33: Enterprise SaaS (final objective) | C33: ENT-07 | D33: Security | E33: Secure internet exposure (BLOCKED) | F33: 0.05 | H33: Not implemented by design: W7 keeps the 127.0.0.1 bind; exposure needs TLS, MFA, rate limiting, security review | I33: Owner decision + security architecture | J33: Owner: Security architecture + decision to expose

Sheet Owner Decisions
A1: # | B1: Decision | C1: Affects | D1: Default now | E1: Why it matters | F1: Your decision | G1: Date
A2: 1 | B2: Turn on the scheduled investor cycle (wealth.enabled) | C2: W11-W17 | D2: off | E2: Daily snapshots, allocation, goal and rebalance checks, wealth alerts. Save your Investor DNA first.
A3: 2 | B3: Enable Claude narration of the advisor (wealth.advisor_llm_enabled) | C3: W16 | D3: off | E3: Sends your holdings/goals evidence pack to Anthropic; needs a working API key.
A4: 3 | B4: Provide a working Anthropic API key | C4: NS-02..04, W16 | D4: key returns 401 | E4: News classification/summary and advisor narration are all blocked; the news catch-up is slow while every call fails.
A5: 4 | B5: VWAP inside the Technical Score (technical.vwap_in_score) | C5: TA-03 | D5: off | E5: Changes every Technical Score, ATIP score and signal.
A6: 5 | B6: prices_daily retention >= 1,100 days | C6: TA-09 | D6: 600 days | E6: Needed for a true 3-year beta; roughly doubles the database.
A7: 6 | B7: Run the technical backfill (python -m data.technical --backfill 426) | C7: TA-12 | D7: not run | E7: Heavy; off-hours, on a copy first.
A8: 7 | B8: Run the factor backfill + research report | C8: QR-01..03, AF-08, MON-05 | D8: 25 sessions only | E8: ~40 s per session for 13 factors; several hours for full history.
A9: 8 | B9: Require approved factors for strategies (quant.require_approved_factors) | C9: AF-08 | D9: off | E9: Blocks promotion of strategies that use unapproved factors.
A10: 9 | B10: Daily anomaly scan (ml.anomalies_enabled) | C10: ML-06 | D10: off | E10: Flags unusual price/volume days.
A11: 10 | B11: Activate an ML model / choose the ML regime provider | C11: SE-05, ML-05 | D11: none active | E11: Validation shows NO_EDGE today: keep off until a report shows EDGE.
A12: 11 | B12: Set the W25 pre-trade limits (volatility / ADV / correlation / portfolio VaR) and portfolio_risk.snapshot_enabled | C12: RK-09..12 | D12: all off | E12: New pre-trade limits and the daily risk snapshot; suggested start: ADV 5%, VaR alert 2% of equity.
A13: 12 | B13: Deploy W25 (portfolio risk) | C13: W25 | D13: branch only | E13: Merge w25-portfolio-risk to master and deploy with deploy_release.ps1.
... A18: 17 | B18: Payment gateway; legal / SEBI review | C18: ENT-04, ENT-14 | D18: not started | E18: Needed before offering ATIP to others.

Sheet Open Issues
A1: ID | B1: Issue | C1: Where | D1: Severity | E1: Status | F1: Seen
A2: OPS-DH15 | B2: dhan_15min_bars job fails every run (0 rows) -- intraday bars cannot be stored | C2: data/dhan.py / broker | D2: Medium | E2: OPEN | F2: 2026-09-25
A3: KD-001 | B3: Anthropic API key returns 401 (news classifier, advisor narration) | C3: .env / config | D3: Medium | E3: OPEN | F3: 2026-09-28
A4: W8-R4 | B4: 7 secrets still in config.json plaintext | C4: atip_data/config.json | D4: Medium | E4: OPEN | F4: 2026-09-28
A5: WLT-1 | B5: LIVE ledger sells inferred at the close until contract notes are entered | C5: wealth/perf/ledger.py | D5: Medium | E5: OPEN | F5: 2026-09-26
A6: WLT-3 | B6: DNA / allocation / scenario methodology not validated against outcomes | C6: wealth/ | D6: Medium | E6: OPEN | F6: 2026-09-26
A7: ML-EDGE | B7: First ML models show NO_EDGE out of sample on 5-day direction | C7: ml/ | D7: Info | E7: OPEN | F7: 2026-09-28
A8: QA-ALL | B8: W3-W24 not independently tested; 70-test wealth suite written, not run | C8: tests/ | D8: High | E8: OPEN | F8: 2026-09-28

Sheet Waves & Deployment
A1: Wave | B1: Scope | C1: Commit | D1: In master | E1: Deployed | F1: Testing
A2: W1 | B2: Foundation: job monitoring, alerts, P&L, loss limits, sizing, data quality | C2: 3c13f63 | D2: yes | E2: Live since 2026-09-28 11:31 (ATIP-W24-RC1) | F2: COMPLETED
A3: W2 | B3: Research / backtesting | C3: ba4028f | D3: yes | E3: Live since 2026-09-28 11:31 (ATIP-W24-RC1) | F3: COMPLETED
A4: W3 | B4: Strategy engine | C4: d563978 | D4: yes | E4: Live since 2026-09-28 11:31 (ATIP-W24-RC1) | F4: Not verified
A5: W4 | B5: Risk and execution (paper) | C5: d3b8715 | D5: yes | E5: Live since 2026-09-28 11:31 (ATIP-W24-RC1) | F5: Not verified
A6: W5 | B6: AI / ML framework | C6: 123b340 | D6: yes | E6: Live since 2026-09-28 11:31 (ATIP-W24-RC1) | F6: Not verified
A7: W6 | B7: Advanced quant | C7: cf1997d | D7: yes | E7: Live since 2026-09-28 11:31 (ATIP-W24-RC1) | F7: Not verified
A8: W7 | B8: Enterprise layer | C8: 3e52bea | D8: yes | E8: Live since 2026-09-28 11:31 (ATIP-W24-RC1) | F8: Not verified
A9: W8 | B9: Production hardening | C9: a7d7187 | D9: yes | E9: Live since 2026-09-28 11:31 (ATIP-W24-RC1) | F9: Not verified
A10: W9 | B10: Release readiness, live-trading master switch | C10: 24943f3 | D10: yes | E10: Live since 2026-09-28 11:31 (ATIP-W24-RC1) | F10: Not verified
A11: W11 | B11: Investor DNA | C11: 1da609f | D11: yes | E11: Live since 2026-09-28 11:31 (ATIP-W24-RC1) | F11: Not verified
A12: W12 | B12: Multi-asset wealth dashboard | C12: 45f0b4b | D12: yes | E12: Live since 2026-09-28 11:31 (ATIP-W24-RC1) | F12: Not verified
... A26: W25 | B26: Portfolio risk: exposure, VaR/ES, correlation, attribution, optimiser, limits, emergency exit | C26: 687b5ac | D26: no (branch w25-portfolio-risk) | E26: Not deployed - needs your authorization | F26: Smoke only
